EasyTrust/__init__.py
EasyTrust/ScoreCard/Score_card.py
EasyTrust/ScoreCard/WOE_encoding_coutinuous.py
EasyTrust/ScoreCard/WOE_encoding_discrete.py
EasyTrust/ScoreCard/__init__.py
EasyTrust/utils/ScoreUtil.py
EasyTrust/utils/__init__.py
TrustUtil-0.1.2.dist-info/LICENSE
TrustUtil-0.1.2.dist-info/METADATA
TrustUtil-0.1.2.dist-info/WHEEL
TrustUtil-0.1.2.dist-info/top_level.txt
TrustUtil-0.1.2.dist-info/RECORD
